mlops/__init__.py
mlops_sdk/__init__.py
mlops_sdk/config/__init__.py
mlops_sdk/data/__init__.py
mlops_sdk/data/batch/__init__.py
mlops_sdk/data/batch/batch.py
mlops_sdk/data/batch/models/__init__.py
mlops_sdk/data/batch/models/batch_models.py
mlops_sdk/data/data/__init__.py
mlops_sdk/data/data/data.py
mlops_sdk/data/datasets/__init__.py
mlops_sdk/data/datasets/dataset.py
mlops_sdk/data/datasets/models/__init__.py
mlops_sdk/data/datasets/models/dataset_models.py
mlops_sdk/data/datasets/models/params/__init__.py
mlops_sdk/data/datasets/models/params/docdb.py
mlops_sdk/data/datasets/models/params/dynamodb.py
mlops_sdk/data/query/__init__.py
mlops_sdk/data/query/query.py
mlops_sdk/experiments/__init__.py
mlops_sdk/experiments/experiment.py
mlops_sdk/ml/__init__.py
mlops_sdk/ml/eo_model.py
mlops_sdk/ml/mlops_model.py
mlops_sdk/ml/model.py
mlops_sdk/ml/model_registry.py
mlops_sdk/mlops_client.py
mlops_sdk/models/__init__.py
mlops_sdk/models/ml_model.py
mlops_sdk/rec/__init__.py
mlops_sdk/rec/channels/__init__.py
mlops_sdk/rec/channels/channel.py
mlops_sdk/rec/channels/models/__init__.py
mlops_sdk/rec/channels/models/channel_models.py
mlops_sdk/rec/experiments/__init__.py
mlops_sdk/rec/experiments/experiment.py
mlops_sdk/rec/experiments/models/__init__.py
mlops_sdk/rec/experiments/models/experiment_models.py
mlops_sdk/rec/recommendations/__init__.py
mlops_sdk/rec/recommendations/models/__init__.py
mlops_sdk/rec/recommendations/models/recommendation_models.py
mlops_sdk/rec/recommendations/recommendation.py
mlops_sdk/slack.py
mlops_sdk/utils/__init__.py
mlops_sdk/utils/datetime_util.py
mlops_sdk/utils/loggers.py
mlops_sdk-2023.1.9.dist-info/WHEEL
mlops_sdk-2023.1.9.dist-info/METADATA
mlops_sdk-2023.1.9.dist-info/RECORD
